<?xml version="1.0" encoding="UTF-8"?>
<!DOCTYPE mapper PUBLIC "-//mybatis.org//DTD Mapper 3.0//EN" "http://mybatis.org/dtd/mybatis-3-mapper.dtd">
<mapper namespace="com.zcjd.app_server.mapper.AttendanceSetPojoMapper">
  <resultMap id="BaseResultMap" type="com.zcjd.app_server.model.AttendanceSetPojo">
    <!--
      WARNING - @mbg.generated
      This element is automatically generated by MyBatis Generator, do not modify.
      This element was generated on Thu Sep 19 10:13:33 CST 2019.
    -->
    <id column="id" jdbcType="VARCHAR" property="id" />
    <id column="work_start_time" jdbcType="VARCHAR" property="workStartTime" />
    <result column="work_day" jdbcType="VARCHAR" property="workDay" />
    <result column="count" jdbcType="INTEGER" property="count" />
    <result column="work_time" jdbcType="VARCHAR" property="workTime" />
    <result column="after_time" jdbcType="VARCHAR" property="afterTime" />
    <result column="work_end_time" jdbcType="VARCHAR" property="workEndTime" />
    <result column="after_start_time" jdbcType="VARCHAR" property="afterStartTime" />
    <result column="after_end_time" jdbcType="VARCHAR" property="afterEndTime" />
    <result column="attendance_day" jdbcType="INTEGER" property="attendanceDay" />
    <result column="delete_state" jdbcType="INTEGER" property="deleteState" />
    <result column="maplng" jdbcType="VARCHAR" property="maplng" />
    <result column="maplat" jdbcType="VARCHAR" property="maplat" />
    <result column="address" jdbcType="VARCHAR" property="address" />
  </resultMap>
  <sql id="Example_Where_Clause">
    <!--
      WARNING - @mbg.generated
      This element is automatically generated by MyBatis Generator, do not modify.
      This element was generated on Thu Sep 19 10:13:33 CST 2019.
    -->
    <where>
      <foreach collection="oredCriteria" item="criteria" separator="or">
        <if test="criteria.valid">
          <trim prefix="(" prefixOverrides="and" suffix=")">
            <foreach collection="criteria.criteria" item="criterion">
              <choose>
                <when test="criterion.noValue">
                  and ${criterion.condition}
                </when>
                <when test="criterion.singleValue">
                  and ${criterion.condition} #{criterion.value}
                </when>
                <when test="criterion.betweenValue">
                  and ${criterion.condition} #{criterion.value} and #{criterion.secondValue}
                </when>
                <when test="criterion.listValue">
                  and ${criterion.condition}
                  <foreach close=")" collection="criterion.value" item="listItem" open="(" separator=",">
                    #{listItem}
                  </foreach>
                </when>
              </choose>
            </foreach>
          </trim>
        </if>
      </foreach>
    </where>
  </sql>
  <sql id="Update_By_Example_Where_Clause">
    <!--
      WARNING - @mbg.generated
      This element is automatically generated by MyBatis Generator, do not modify.
      This element was generated on Thu Sep 19 10:13:33 CST 2019.
    -->
    <where>
      <foreach collection="example.oredCriteria" item="criteria" separator="or">
        <if test="criteria.valid">
          <trim prefix="(" prefixOverrides="and" suffix=")">
            <foreach collection="criteria.criteria" item="criterion">
              <choose>
                <when test="criterion.noValue">
                  and ${criterion.condition}
                </when>
                <when test="criterion.singleValue">
                  and ${criterion.condition} #{criterion.value}
                </when>
                <when test="criterion.betweenValue">
                  and ${criterion.condition} #{criterion.value} and #{criterion.secondValue}
                </when>
                <when test="criterion.listValue">
                  and ${criterion.condition}
                  <foreach close=")" collection="criterion.value" item="listItem" open="(" separator=",">
                    #{listItem}
                  </foreach>
                </when>
              </choose>
            </foreach>
          </trim>
        </if>
      </foreach>
    </where>
  </sql>
  <sql id="Base_Column_List">
    <!--
      WARNING - @mbg.generated
      This element is automatically generated by MyBatis Generator, do not modify.
      This element was generated on Thu Sep 19 10:13:33 CST 2019.
    -->
    id, work_start_time, work_day, count, work_time, after_time, work_end_time, after_start_time, 
    after_end_time, attendance_day, delete_state, maplng, maplat, address
  </sql>
  <select id="selectWeek"
          parameterType="java.lang.Integer"
          resultMap="BaseResultMap">
    SELECT
    <include refid="Base_Column_List" />
    FROM hr_attendance_set WHERE FIND_IN_SET(#{week},work_day) and delete_state=0
  </select>
  <select id="selectByExample" parameterType="com.zcjd.app_server.model.AttendanceSetPojoExample" resultMap="BaseResultMap">
    <!--
      WARNING - @mbg.generated
      This element is automatically generated by MyBatis Generator, do not modify.
      This element was generated on Thu Sep 19 10:13:33 CST 2019.
    -->
    select
    <if test="distinct">
      distinct
    </if>
    <include refid="Base_Column_List" />
    from hr_attendance_set
    <if test="_parameter != null">
      <include refid="Example_Where_Clause" />
    </if>
    <if test="orderByClause != null">
      order by ${orderByClause}
    </if>
  </select>
  <select id="selectByPrimaryKey" parameterType="com.zcjd.app_server.model.AttendanceSetPojoKey" resultMap="BaseResultMap">
    <!--
      WARNING - @mbg.generated
      This element is automatically generated by MyBatis Generator, do not modify.
      This element was generated on Thu Sep 19 10:13:33 CST 2019.
    -->
    select 
    <include refid="Base_Column_List" />
    from hr_attendance_set
    where id = #{id,jdbcType=VARCHAR}
      and work_start_time = #{workStartTime,jdbcType=VARCHAR}
  </select>
  <delete id="deleteByPrimaryKey" parameterType="com.zcjd.app_server.model.AttendanceSetPojoKey">
    <!--
      WARNING - @mbg.generated
      This element is automatically generated by MyBatis Generator, do not modify.
      This element was generated on Thu Sep 19 10:13:33 CST 2019.
    -->
    delete from hr_attendance_set
    where id = #{id,jdbcType=VARCHAR}
      and work_start_time = #{workStartTime,jdbcType=VARCHAR}
  </delete>
  <delete id="deleteByExample" parameterType="com.zcjd.app_server.model.AttendanceSetPojoExample">
    <!--
      WARNING - @mbg.generated
      This element is automatically generated by MyBatis Generator, do not modify.
      This element was generated on Thu Sep 19 10:13:33 CST 2019.
    -->
    delete from hr_attendance_set
    <if test="_parameter != null">
      <include refid="Example_Where_Clause" />
    </if>
  </delete>
  <insert id="insert" parameterType="com.zcjd.app_server.model.AttendanceSetPojo">
    <!--
      WARNING - @mbg.generated
      This element is automatically generated by MyBatis Generator, do not modify.
      This element was generated on Thu Sep 19 10:13:33 CST 2019.
    -->
    insert into hr_attendance_set (id, work_start_time, work_day, 
      count, work_time, after_time, 
      work_end_time, after_start_time, after_end_time, 
      attendance_day, delete_state, maplng, 
      maplat, address)
    values (#{id,jdbcType=VARCHAR}, #{workStartTime,jdbcType=VARCHAR}, #{workDay,jdbcType=VARCHAR}, 
      #{count,jdbcType=INTEGER}, #{workTime,jdbcType=VARCHAR}, #{afterTime,jdbcType=VARCHAR}, 
      #{workEndTime,jdbcType=VARCHAR}, #{afterStartTime,jdbcType=VARCHAR}, #{afterEndTime,jdbcType=VARCHAR}, 
      #{attendanceDay,jdbcType=INTEGER}, #{deleteState,jdbcType=INTEGER}, #{maplng,jdbcType=VARCHAR}, 
      #{maplat,jdbcType=VARCHAR}, #{address,jdbcType=VARCHAR})
  </insert>
  <insert id="insertSelective" parameterType="com.zcjd.app_server.model.AttendanceSetPojo">
    <!--
      WARNING - @mbg.generated
      This element is automatically generated by MyBatis Generator, do not modify.
      This element was generated on Thu Sep 19 10:13:33 CST 2019.
    -->
    insert into hr_attendance_set
    <trim prefix="(" suffix=")" suffixOverrides=",">
      <if test="id != null">
        id,
      </if>
      <if test="workStartTime != null">
        work_start_time,
      </if>
      <if test="workDay != null">
        work_day,
      </if>
      <if test="count != null">
        count,
      </if>
      <if test="workTime != null">
        work_time,
      </if>
      <if test="afterTime != null">
        after_time,
      </if>
      <if test="workEndTime != null">
        work_end_time,
      </if>
      <if test="afterStartTime != null">
        after_start_time,
      </if>
      <if test="afterEndTime != null">
        after_end_time,
      </if>
      <if test="attendanceDay != null">
        attendance_day,
      </if>
      <if test="deleteState != null">
        delete_state,
      </if>
      <if test="maplng != null">
        maplng,
      </if>
      <if test="maplat != null">
        maplat,
      </if>
      <if test="address != null">
        address,
      </if>
    </trim>
    <trim prefix="values (" suffix=")" suffixOverrides=",">
      <if test="id != null">
        #{id,jdbcType=VARCHAR},
      </if>
      <if test="workStartTime != null">
        #{workStartTime,jdbcType=VARCHAR},
      </if>
      <if test="workDay != null">
        #{workDay,jdbcType=VARCHAR},
      </if>
      <if test="count != null">
        #{count,jdbcType=INTEGER},
      </if>
      <if test="workTime != null">
        #{workTime,jdbcType=VARCHAR},
      </if>
      <if test="afterTime != null">
        #{afterTime,jdbcType=VARCHAR},
      </if>
      <if test="workEndTime != null">
        #{workEndTime,jdbcType=VARCHAR},
      </if>
      <if test="afterStartTime != null">
        #{afterStartTime,jdbcType=VARCHAR},
      </if>
      <if test="afterEndTime != null">
        #{afterEndTime,jdbcType=VARCHAR},
      </if>
      <if test="attendanceDay != null">
        #{attendanceDay,jdbcType=INTEGER},
      </if>
      <if test="deleteState != null">
        #{deleteState,jdbcType=INTEGER},
      </if>
      <if test="maplng != null">
        #{maplng,jdbcType=VARCHAR},
      </if>
      <if test="maplat != null">
        #{maplat,jdbcType=VARCHAR},
      </if>
      <if test="address != null">
        #{address,jdbcType=VARCHAR},
      </if>
    </trim>
  </insert>
  <select id="countByExample" parameterType="com.zcjd.app_server.model.AttendanceSetPojoExample" resultType="java.lang.Long">
    <!--
      WARNING - @mbg.generated
      This element is automatically generated by MyBatis Generator, do not modify.
      This element was generated on Thu Sep 19 10:13:33 CST 2019.
    -->
    select count(*) from hr_attendance_set
    <if test="_parameter != null">
      <include refid="Example_Where_Clause" />
    </if>
  </select>
  <update id="updateByExampleSelective" parameterType="map">
    <!--
      WARNING - @mbg.generated
      This element is automatically generated by MyBatis Generator, do not modify.
      This element was generated on Thu Sep 19 10:13:33 CST 2019.
    -->
    update hr_attendance_set
    <set>
      <if test="record.id != null">
        id = #{record.id,jdbcType=VARCHAR},
      </if>
      <if test="record.workStartTime != null">
        work_start_time = #{record.workStartTime,jdbcType=VARCHAR},
      </if>
      <if test="record.workDay != null">
        work_day = #{record.workDay,jdbcType=VARCHAR},
      </if>
      <if test="record.count != null">
        count = #{record.count,jdbcType=INTEGER},
      </if>
      <if test="record.workTime != null">
        work_time = #{record.workTime,jdbcType=VARCHAR},
      </if>
      <if test="record.afterTime != null">
        after_time = #{record.afterTime,jdbcType=VARCHAR},
      </if>
      <if test="record.workEndTime != null">
        work_end_time = #{record.workEndTime,jdbcType=VARCHAR},
      </if>
      <if test="record.afterStartTime != null">
        after_start_time = #{record.afterStartTime,jdbcType=VARCHAR},
      </if>
      <if test="record.afterEndTime != null">
        after_end_time = #{record.afterEndTime,jdbcType=VARCHAR},
      </if>
      <if test="record.attendanceDay != null">
        attendance_day = #{record.attendanceDay,jdbcType=INTEGER},
      </if>
      <if test="record.deleteState != null">
        delete_state = #{record.deleteState,jdbcType=INTEGER},
      </if>
      <if test="record.maplng != null">
        maplng = #{record.maplng,jdbcType=VARCHAR},
      </if>
      <if test="record.maplat != null">
        maplat = #{record.maplat,jdbcType=VARCHAR},
      </if>
      <if test="record.address != null">
        address = #{record.address,jdbcType=VARCHAR},
      </if>
    </set>
    <if test="_parameter != null">
      <include refid="Update_By_Example_Where_Clause" />
    </if>
  </update>
  <update id="updateByExample" parameterType="map">
    <!--
      WARNING - @mbg.generated
      This element is automatically generated by MyBatis Generator, do not modify.
      This element was generated on Thu Sep 19 10:13:33 CST 2019.
    -->
    update hr_attendance_set
    set id = #{record.id,jdbcType=VARCHAR},
      work_start_time = #{record.workStartTime,jdbcType=VARCHAR},
      work_day = #{record.workDay,jdbcType=VARCHAR},
      count = #{record.count,jdbcType=INTEGER},
      work_time = #{record.workTime,jdbcType=VARCHAR},
      after_time = #{record.afterTime,jdbcType=VARCHAR},
      work_end_time = #{record.workEndTime,jdbcType=VARCHAR},
      after_start_time = #{record.afterStartTime,jdbcType=VARCHAR},
      after_end_time = #{record.afterEndTime,jdbcType=VARCHAR},
      attendance_day = #{record.attendanceDay,jdbcType=INTEGER},
      delete_state = #{record.deleteState,jdbcType=INTEGER},
      maplng = #{record.maplng,jdbcType=VARCHAR},
      maplat = #{record.maplat,jdbcType=VARCHAR},
      address = #{record.address,jdbcType=VARCHAR}
    <if test="_parameter != null">
      <include refid="Update_By_Example_Where_Clause" />
    </if>
  </update>
  <update id="updateByPrimaryKeySelective" parameterType="com.zcjd.app_server.model.AttendanceSetPojo">
    <!--
      WARNING - @mbg.generated
      This element is automatically generated by MyBatis Generator, do not modify.
      This element was generated on Thu Sep 19 10:13:33 CST 2019.
    -->
    update hr_attendance_set
    <set>
      <if test="workDay != null">
        work_day = #{workDay,jdbcType=VARCHAR},
      </if>
      <if test="count != null">
        count = #{count,jdbcType=INTEGER},
      </if>
      <if test="workTime != null">
        work_time = #{workTime,jdbcType=VARCHAR},
      </if>
      <if test="afterTime != null">
        after_time = #{afterTime,jdbcType=VARCHAR},
      </if>
      <if test="workEndTime != null">
        work_end_time = #{workEndTime,jdbcType=VARCHAR},
      </if>
      <if test="afterStartTime != null">
        after_start_time = #{afterStartTime,jdbcType=VARCHAR},
      </if>
      <if test="afterEndTime != null">
        after_end_time = #{afterEndTime,jdbcType=VARCHAR},
      </if>
      <if test="attendanceDay != null">
        attendance_day = #{attendanceDay,jdbcType=INTEGER},
      </if>
      <if test="deleteState != null">
        delete_state = #{deleteState,jdbcType=INTEGER},
      </if>
      <if test="maplng != null">
        maplng = #{maplng,jdbcType=VARCHAR},
      </if>
      <if test="maplat != null">
        maplat = #{maplat,jdbcType=VARCHAR},
      </if>
      <if test="address != null">
        address = #{address,jdbcType=VARCHAR},
      </if>
    </set>
    where id = #{id,jdbcType=VARCHAR}
      and work_start_time = #{workStartTime,jdbcType=VARCHAR}
  </update>
  <update id="updateByPrimaryKey" parameterType="com.zcjd.app_server.model.AttendanceSetPojo">
    <!--
      WARNING - @mbg.generated
      This element is automatically generated by MyBatis Generator, do not modify.
      This element was generated on Thu Sep 19 10:13:33 CST 2019.
    -->
    update hr_attendance_set
    set work_day = #{workDay,jdbcType=VARCHAR},
      count = #{count,jdbcType=INTEGER},
      work_time = #{workTime,jdbcType=VARCHAR},
      after_time = #{afterTime,jdbcType=VARCHAR},
      work_end_time = #{workEndTime,jdbcType=VARCHAR},
      after_start_time = #{afterStartTime,jdbcType=VARCHAR},
      after_end_time = #{afterEndTime,jdbcType=VARCHAR},
      attendance_day = #{attendanceDay,jdbcType=INTEGER},
      delete_state = #{deleteState,jdbcType=INTEGER},
      maplng = #{maplng,jdbcType=VARCHAR},
      maplat = #{maplat,jdbcType=VARCHAR},
      address = #{address,jdbcType=VARCHAR}
    where id = #{id,jdbcType=VARCHAR}
      and work_start_time = #{workStartTime,jdbcType=VARCHAR}
  </update>
</mapper>